html2cleantext/__init__.py
html2cleantext/cleaners.py
html2cleantext/cli.py
html2cleantext/core.py
html2cleantext/utils.py
html2cleantext-0.1.6.dist-info/licenses/LICENSE
html2cleantext-0.1.6.dist-info/METADATA
html2cleantext-0.1.6.dist-info/WHEEL
html2cleantext-0.1.6.dist-info/entry_points.txt
html2cleantext-0.1.6.dist-info/top_level.txt
html2cleantext-0.1.6.dist-info/RECORD
