Metadata-Version: 2.4
Name: html2cleantext
Version: 0.1.6
Summary: Convert HTML to clean, structured Markdown or plain text
Home-page: https://github.com/Shawn-Imran/html2cleantext
Author: Md Al Mahmud Imran
Author-email: Md Al Mahmud Imran <md.almahmudimran@gmail.com>
License: MIT
Project-URL: Homepage, https://github.com/Shawn-Imran/html2cleantext
Project-URL: Bug Reports, https://github.com/Shawn-Imran/html2cleantext/issues
Project-URL: Source, https://github.com/Shawn-Imran/html2cleantext
Keywords: html,markdown,text,cleaning,boilerplate,nlp
Classifier: Development Status :: 3 - Alpha
Classifier: Intended Audience :: Developers
Classifier: License :: OSI Approved :: MIT License
Classifier: Operating System :: OS Independent
Classifier: Programming Language :: Python :: 3
Classifier: Programming Language :: Python :: 3.7
Classifier: Programming Language :: Python :: 3.8
Classifier: Programming Language :: Python :: 3.9
Classifier: Programming Language :: Python :: 3.10
Classifier: Programming Language :: Python :: 3.11
Classifier: Topic :: Software Development :: Libraries :: Python Modules
Classifier: Topic :: Text Processing :: Markup :: HTML
Classifier: Topic :: Text Processing :: Markup :: Markdown
Requires-Python: >=3.7
License-File: LICENSE
Requires-Dist: beautifulsoup4>=4.9.0
Requires-Dist: lxml>=4.6.0
Requires-Dist: markdownify>=0.11.0
Requires-Dist: readability-lxml>=0.8.0
Requires-Dist: langdetect>=1.0.9
Requires-Dist: requests>=2.25.0
Dynamic: author
Dynamic: home-page
Dynamic: license-file
